docx2latex/__init__.py
docx2latex/myutility.py
docx2latex-0.0.4.dist-info/LICENSE.txt
docx2latex-0.0.4.dist-info/METADATA
docx2latex-0.0.4.dist-info/WHEEL
docx2latex-0.0.4.dist-info/top_level.txt
docx2latex-0.0.4.dist-info/RECORD
