Metadata-Version: 2.1
Name: docx2latex
Version: 0.0.4
Summary: convert docx file to html code including latex linear equation
Author: shadan
Author-email: shadanparvez64@gmail.com
Classifier: Development Status :: 2 - Pre-Alpha
Classifier: Programming Language :: Python :: 3
Classifier: License :: OSI Approved :: MIT License
Classifier: Operating System :: OS Independent
Requires-Python: >=3.6
License-File: LICENSE.txt
